{
    "Actor": {
        "types": ["Jugador","PNJ"],
            "Jugador": {
                "Salud": {
                    "value": 0,
                    "max": 0,
                    "min": 0
                },
                "Estabilidad": {
                  "value": 0,
                  "max": 0,
                  "min": 0
                },
                "Poder": {
                  "value": 0,
                  "max": 0,
                  "min": 0
                },
                "Proezas": {
                  "value": 0,
                  "max": 0,
                  "min": 0
                },
                "Carisma": 0,
                "Destreza": 0,
                "Fuerza": 0,
                "Inteligencia": 0,
                "Percepción": 0,
                "Agilidad": {
                  "Valor": 0,
                  "Bono": 0
                  },
                "Aplomo": {
                  "Valor": 0,
                  "Bono": 0
                  },
                "Perspicacia": {
                  "Valor": 0,
                  "Bono": 0
                  },
                "Resistencia_Física": 0,
                "Resistencia_Mental": 0,
                "Protección_Daño": 0,
                "Protección_Agilidad": 0,
                "Protección_Penalización": 0,
                "Iniciativa": 0,
                "Recuerdo_Cuando": "false",
                "Recuerdo_Cuando_Activo": "false",
                "Habilidades": {
                  "Atletismo":{
                    "Nombre": "Atletismo",
                    "Valor": 1,
                    "Atributo": "Destreza"
                  },
                  "Auxilio":{
                    "Nombre": "Auxilio",
                    "Valor": 1,
                    "Atributo": "Inteligencia"
                  },
                  "Conducir":{
                    "Nombre": "Conducir",
                    "Valor": 1,
                    "Atributo": "Destreza"
                  },
                  "Conversación":{
                    "Nombre": "Conversación",
                    "Valor": 1,
                    "Atributo": "Carisma"
                  },
                  "Cultura":{
                    "Nombre": "Cultura",
                    "Valor": 1,
                    "Atributo": "Inteligencia"
                  },
                  "Entorno":{
                    "Nombre": "Entorno",
                    "Valor": 1,
                    "Atributo": "Percepción"
                  },
                  "Fuerza_bruta":{
                    "Nombre": "Fuerza bruta",
                    "Valor": 1,
                    "Atributo": "Fuerza"
                  },
                  "Idioma_ext_1":{
                    "Nombre": "Idioma ext. [1]",
                    "Valor": 1,
                    "Atributo": "Inteligencia"
                  },
                  "Idioma_ext_2":{
                    "Nombre": "Idioma ext. [2]",
                    "Valor": 1,
                    "Atributo": "Inteligencia"
                  },
                  "Información":{
                    "Nombre": "Información",
                    "Valor": 1,
                    "Atributo": "Inteligencia"
                  },
                  "Intimidación":{
                    "Nombre": "Intimidación",
                    "Valor": 1,
                    "Atributo": "Carisma"
                  },
                  "Lucha":{
                    "Nombre": "Lucha",
                    "Valor": 1,
                    "Atributo": "Destreza"
                  },
                  "Mecánica":{
                    "Nombre": "Mecánica",
                    "Valor": 1,
                    "Atributo": "Inteligencia"
                  },
                  "Memoria":{
                    "Nombre": "Memoria",
                    "Valor": 1,
                    "Atributo": "Inteligencia"
                  },
                  "Observación":{
                    "Nombre": "Observación",
                    "Valor": 1,
                    "Atributo": "Percepción"
                  },
                  "Ocultación":{
                    "Nombre": "Ocultación",
                    "Valor": 1,
                    "Atributo": "Destreza"
                  },
                  "Oído":{
                    "Nombre": "Oído",
                    "Valor": 1,
                    "Atributo": "Percepción"
                  },
                  "Psicología":{
                    "Nombre": "Psicología",
                    "Valor": 1,
                    "Atributo": "Percepción"
                  },
                  "Puntería":{
                    "Nombre": "Puntería",
                    "Valor": 1,
                    "Atributo": "Percepción"
                  },
                  "Rastreo":{
                    "Nombre": "Rastreo",
                    "Valor": 1,
                    "Atributo": "Percepción"
                  },
                  "Seducción":{
                    "Nombre": "Seducción",
                    "Valor": 1,
                    "Atributo": "Carisma"
                  },
                  "Sigilo":{
                    "Nombre": "Sigilo",
                    "Valor": 1,
                    "Atributo": "Destreza"
                  },
                  "Simulación":{
                    "Nombre": "Simulación",
                    "Valor": 1,
                    "Atributo": "Carisma"
                  },
                  "Supervivencia":{
                    "Nombre": "Supervivencia",
                    "Valor": 1,
                    "Atributo": "Percepción"
                  }
                },
                "Profesión": "",
                "Defecto_Leve": "",
                "Defecto_Grave": "",
                "Talento": "",
                "Arquetipo": "",
                "Biografía": "",
                "Experiencia": 0,
                "Magia":{
                  "Nombre": "Magia/Psiónica",
                  "Valor": 1,
                  "Atributo": "Inteligencia"
                }
            },
            "PNJ": {
              "Salud": {
                  "value": 0,
                  "max": 0,
                  "min": 0
              },
              "Poder": {
                "value": 0,
                "max": 0,
                "min": 0
              },
              "Carisma": 0,
              "Destreza": 0,
              "Fuerza": 0,
              "Inteligencia": 0,
              "Percepción": 0,
              "Agilidad": 0,
              "Aplomo": 0,
              "Perspicacia": 0,
              "Resistencia_Física": 0,
              "Protección_Daño": 0,
              "Protección_Agilidad": 0,
              "Protección_Penalización": 0,
              "Iniciativa": 0,
              "Habilidades": {
                "Atletismo":{
                  "Valor": 1,
                  "Atributo": "Destreza"
                },
                "Lucha":{
                  "Valor": 1,
                  "Atributo": "Destreza"
                },
                "Puntería":{
                  "Valor": 1,
                  "Atributo": "Percepción"
                }
              },
              "Biografía": ""
            }

    },
    "Item":{
    "types": ["Arma", "Armadura", "Escudo", "Objeto", "Poder"],
    "Arma":{
      "Habilidad": "Lucha",
      "Daño": 0,
      "Bono": "FUE",
      "Ataque": "",
      "Daño_Total": 0,
      "Equipado": "false",
      "Descripción": ""
    },
    "Armadura":{
      "Nivel": 0,
      "Penalizador": 0,
      "Equipado": "false",
      "Descripción": ""
    },
    "Escudo":{
      "Nivel": 0,
      "Penalizador": 0,
      "Equipado": "false",
      "Descripción": ""
    },
    "Objeto":{
      "Cantidad": 0,
      "Descripción": ""
    },
    "Poder":{
      "Tipo": "",
      "Atributo": "",
      "Dificultad": "",
      "Descripción": "",
      "Preparación": "",
      "Lanzamiento": "",
      "Duración": "",
      "Caducidad": ""
    }
  }
}
